opentick/__init__.py
opentick/client.py
opentick-1.2.0.dist-info/LICENSE
opentick-1.2.0.dist-info/METADATA
opentick-1.2.0.dist-info/WHEEL
opentick-1.2.0.dist-info/top_level.txt
opentick-1.2.0.dist-info/RECORD
