Metadata-Version: 2.1
Name: opentick
Version: 1.2.0
Summary: OpenTick SDK
Home-page: https://github.com/opentradesolutions/opentick
Author: OpenTrade Solutions
Author-email: info@opentradesolutions.com
License: Apache License
Platform: UNKNOWN
Classifier: Intended Audience :: Developers
Classifier: Operating System :: OS Independent
Classifier: Programming Language :: Python
Classifier: Programming Language :: Python :: 2.7
Classifier: Programming Language :: Python :: 3
Classifier: Programming Language :: Python :: 3.4
Classifier: Programming Language :: Python :: 3.5
Classifier: Programming Language :: Python :: 3.6
Classifier: Topic :: Software Development :: Libraries
Classifier: Topic :: Software Development :: Libraries :: Python Modules
Classifier: Topic :: Database :: Database Engines/Servers
Classifier: Intended Audience :: Information Technology
Classifier: Intended Audience :: Financial and Insurance Industry
Requires-Dist: pytz
Requires-Dist: six (>=1.10.0)
Requires-Dist: pymongo (>=3.7.0)
